winsspi/__init__.py
winsspi/_version.py
winsspi/sspi.py
winsspi/common/__init__.py
winsspi/common/defines.py
winsspi/common/function_defs.py
winsspi/common/gssapi/__init__.py
winsspi/common/gssapi/asn1_structs.py
winsspi/utils/__init__.py
winsspi/utils/ldap3_gssapi_patch.py
winsspi/utils/ldap3_patch.py
winsspi-0.0.11.dist-info/LICENSE
winsspi-0.0.11.dist-info/METADATA
winsspi-0.0.11.dist-info/WHEEL
winsspi-0.0.11.dist-info/top_level.txt
winsspi-0.0.11.dist-info/zip-safe
winsspi-0.0.11.dist-info/RECORD
