Metadata-Version: 2.1
Name: winsspi
Version: 0.0.11
Summary: Windows SSPI library in pure Python
Home-page: https://github.com/skelsec/winsspi
Author: Tamas Jos
Author-email: info@skelsecprojects.com
Classifier: Programming Language :: Python :: 3.6
Classifier: License :: OSI Approved :: MIT License
Classifier: Operating System :: OS Independent
Requires-Python: >=3.6
License-File: LICENSE
